incremental_backup/__init__.py
incremental_backup/__main__.py
incremental_backup/path_exclude.py
incremental_backup/prune.py
incremental_backup/restore.py
incremental_backup/_utility/__init__.py
incremental_backup/_utility/console.py
incremental_backup/_utility/path.py
incremental_backup/backup/__init__.py
incremental_backup/backup/backup.py
incremental_backup/backup/filesystem.py
incremental_backup/backup/plan.py
incremental_backup/backup/sum.py
incremental_backup/cli/__init__.py
incremental_backup/cli/main.py
incremental_backup/cli/command/__init__.py
incremental_backup/cli/command/backup.py
incremental_backup/cli/command/command.py
incremental_backup/cli/command/exception.py
incremental_backup/cli/command/prune.py
incremental_backup/cli/command/registry.py
incremental_backup/cli/command/restore.py
incremental_backup/meta/__init__.py
incremental_backup/meta/complete_info.py
incremental_backup/meta/manifest.py
incremental_backup/meta/meta.py
incremental_backup/meta/start_info.py
incremental_backup-1.3.0.dist-info/LICENCE.txt
incremental_backup-1.3.0.dist-info/METADATA
incremental_backup-1.3.0.dist-info/WHEEL
incremental_backup-1.3.0.dist-info/entry_points.txt
incremental_backup-1.3.0.dist-info/top_level.txt
incremental_backup-1.3.0.dist-info/RECORD
