Metadata-Version: 2.1
Name: incremental_backup
Version: 1.3.0
Summary: Incremental file backup tool
Author-email: Reece Jones <reece.jones131@gmail.com>
Project-URL: Homepage, https://github.com/MC-DeltaT/IncrementalBackup2
Project-URL: Issues, https://github.com/MC-DeltaT/IncrementalBackup2/issues
Classifier: Programming Language :: Python :: 3
Classifier: Operating System :: OS Independent
Classifier: License :: OSI Approved :: GNU General Public License v3 (GPLv3)
Classifier: Natural Language :: English
Requires-Python: >=3.9
License-File: LICENCE.txt
